RobotVidSub/__init__.py
RobotVidSub/listener.py
RobotVidSub-0.1.0.dist-info/LICENSE
RobotVidSub-0.1.0.dist-info/METADATA
RobotVidSub-0.1.0.dist-info/WHEEL
RobotVidSub-0.1.0.dist-info/entry_points.txt
RobotVidSub-0.1.0.dist-info/top_level.txt
RobotVidSub-0.1.0.dist-info/RECORD
