Metadata-Version: 2.1
Name: RobotVidSub
Version: 0.1.0
Summary: Enhance Robot Framework tests by recording and subtitling videos.
Home-page: https://github.com/Arkasaur/RobotVidSub
Author: Arka Mitra
Author-email: arkamitra172@gmail.com
License: LICENSE.txt
Classifier: Programming Language :: Python
Classifier: Programming Language :: Python :: 3
Classifier: Framework :: Robot Framework
Classifier: Topic :: Software Development :: Testing
Classifier: License :: OSI Approved :: MIT License
Classifier: Operating System :: OS Independent
License-File: LICENSE
Requires-Dist: robotframework >=3.0
Requires-Dist: ffmpeg-python
Requires-Dist: robotframework-screencaplibrary
